{
    "manager_prompt": {
        "type": "template",
        "content": "Solve {task_type} task with Thought, Action, Observation steps. Actions:\n(1) Search[requirements] — search using Searcher agent\n(2) Finish[response] — complete task\n\nMax steps: {max_step}\n\nTask Requirements: {task_prompt}\nConversation History: {history}\n{examples}\n{scratchpad}"
    },
    "manager_prompt_json": {
        "type": "template",
        "content": "Solve {task_type} task with Thought, Action, Observation steps. Actions (JSON):\n(1) {{\"type\": \"Search\", \"content\": requirements}} — search using Searcher agent\n(2) {{\"type\": \"Finish\", \"content\": response}} — complete task\n\nMax steps: {max_step}\n\nTask Requirements: {task_prompt}\nConversation History: {history}\n{examples}\n{scratchpad}"
    },
    "hint": {
        "type": "raw",
        "content": "Use Finish Action to complete the task."
    },
    "valid_action_example": {
        "type": "raw",
        "content": "Search[Schindler's list]\nFinish[{finish}]"
    },
    "valid_action_example_json": {
        "type": "raw",
        "content": "{\"type\": \"search\", \"content\": \"Schindler's list\"}\n{\"type\": \"finish\", \"content\": {finish}}"
    }
}